pyreferrer/__init__.py
pyreferrer/referrer.py
pyreferrer/referrer_test.py
pyreferrer/ruleset.py
pyreferrer/data/referrers.json
pyreferrer-0.6.6.dist-info/LICENSE
pyreferrer-0.6.6.dist-info/METADATA
pyreferrer-0.6.6.dist-info/WHEEL
pyreferrer-0.6.6.dist-info/top_level.txt
pyreferrer-0.6.6.dist-info/RECORD
