Metadata-Version: 2.1
Name: pyreferrer
Version: 0.6.6
Summary: A referrer parser for Python.
Home-page: http://github.com/Shopify/pyreferrer
Author: Shopify Data Acceleration
Author-email: data-acceleration@shopify.com
License: MIT
Platform: UNKNOWN
Classifier: License :: OSI Approved :: MIT License
Classifier: Programming Language :: Python
Classifier: Programming Language :: Python :: 2.7
Classifier: Programming Language :: Python :: 3
Classifier: Programming Language :: Python :: 3.3
Classifier: Programming Language :: Python :: 3.4
Classifier: Programming Language :: Python :: 3.5
Classifier: Programming Language :: Python :: 3.6
Classifier: Programming Language :: Python :: 3.7
License-File: LICENSE
Requires-Dist: tldextract (<=2.2.1,>=2.0.2)
Requires-Dist: six (>=1.11.0)
Provides-Extra: test
Requires-Dist: nose ; extra == 'test'
